azubar/__init__.py
azubar/azubar.py
azubar/bars.py
azubar/helper.py
azubar-0.0.3.2.dist-info/licenses/LICENSE
azubar-0.0.3.2.dist-info/METADATA
azubar-0.0.3.2.dist-info/WHEEL
azubar-0.0.3.2.dist-info/top_level.txt
azubar-0.0.3.2.dist-info/RECORD
