Metadata-Version: 2.4
Name: azubar
Version: 0.0.3.2
Summary: A progerss bar creator
Home-page: https://github.com/Kazekawa-azusa/azubar
Author: Kazekawa-azusa
License: MIT
Classifier: Programming Language :: Python :: 3.11
Classifier: License :: OSI Approved :: MIT License
Classifier: Operating System :: OS Independent
Requires-Python: >=3.11
License-File: LICENSE
Dynamic: author
Dynamic: classifier
Dynamic: description
Dynamic: description-content-type
Dynamic: home-page
Dynamic: license
Dynamic: license-file
Dynamic: requires-python
Dynamic: summary
